README.md
setup.py
tap_insided/__init__.py
tap_insided/client.py
tap_insided/discover.py
tap_insided/endpoints.py
tap_insided/sync.py
tap_insided.egg-info/PKG-INFO
tap_insided.egg-info/SOURCES.txt
tap_insided.egg-info/dependency_links.txt
tap_insided.egg-info/entry_points.txt
tap_insided.egg-info/requires.txt
tap_insided.egg-info/top_level.txt
tap_insided/schemas/article_poll_results.json
tap_insided/schemas/article_replies.json
tap_insided/schemas/articles.json
tap_insided/schemas/categories.json
tap_insided/schemas/conversation_replies.json
tap_insided/schemas/conversations.json
tap_insided/schemas/events.json
tap_insided/schemas/product_areas.json
tap_insided/schemas/product_update_replies.json
tap_insided/schemas/product_updates.json
tap_insided/schemas/question_replies.json
tap_insided/schemas/questions.json
tap_insided/schemas/tags.json
tap_insided/schemas/topics.json
tap_insided/schemas/user_activities.json
tap_insided/schemas/users.json