Metadata-Version: 2.1
Name: tap-insided
Version: 0.0.2
Summary: Singer.io tap for extracting data from the inSided API
Home-page: UNKNOWN
License: UNKNOWN
Platform: UNKNOWN
Classifier: Programming Language :: Python :: 3 :: Only
Provides-Extra: dev
